setup.py
wav2image/__init__.py
wav2image.egg-info/PKG-INFO
wav2image.egg-info/SOURCES.txt
wav2image.egg-info/dependency_links.txt
wav2image.egg-info/entry_points.txt
wav2image.egg-info/requires.txt
wav2image.egg-info/top_level.txt